ellipse/__init__.py
ellipse/datasets.py
ellipse-0.6.0.dist-info/METADATA
ellipse-0.6.0.dist-info/WHEEL
ellipse-0.6.0.dist-info/top_level.txt
ellipse-0.6.0.dist-info/RECORD
